odoo/addons/web_notify/README.rst
odoo/addons/web_notify/__init__.py
odoo/addons/web_notify/__manifest__.py
odoo/addons/web_notify/i18n/da.po
odoo/addons/web_notify/i18n/de.po
odoo/addons/web_notify/i18n/es.po
odoo/addons/web_notify/i18n/hr.po
odoo/addons/web_notify/i18n/it.po
odoo/addons/web_notify/i18n/nl.po
odoo/addons/web_notify/i18n/nl_NL.po
odoo/addons/web_notify/i18n/pt_BR.po
odoo/addons/web_notify/i18n/web_notify.pot
odoo/addons/web_notify/i18n/zh_CN.po
odoo/addons/web_notify/models/__init__.py
odoo/addons/web_notify/models/res_users.py
odoo/addons/web_notify/readme/CONTRIBUTORS.md
odoo/addons/web_notify/readme/CREDITS.md
odoo/addons/web_notify/readme/DESCRIPTION.md
odoo/addons/web_notify/readme/INSTALL.md
odoo/addons/web_notify/readme/USAGE.md
odoo/addons/web_notify/static/description/icon.png
odoo/addons/web_notify/static/description/index.html
odoo/addons/web_notify/static/img/notifications_screenshot.gif
odoo/addons/web_notify/static/img/test_notifications_demo.png
odoo/addons/web_notify/static/src/js/services/notification.esm.js
odoo/addons/web_notify/static/src/js/services/notification_services.esm.js
odoo/addons/web_notify/tests/__init__.py
odoo/addons/web_notify/tests/test_res_users.py
odoo/addons/web_notify/views/res_users_demo.xml
odoo_addon_web_notify-18.0.1.1.1.dist-info/METADATA
odoo_addon_web_notify-18.0.1.1.1.dist-info/WHEEL
odoo_addon_web_notify-18.0.1.1.1.dist-info/top_level.txt
odoo_addon_web_notify-18.0.1.1.1.dist-info/RECORD
