Metadata-Version: 2.1
Name: odoo-addon-web_notify
Version: 18.0.1.1.1
Requires-Python: >=3.10
Requires-Dist: odoo==18.0.*
Summary: Send notification messages to user
Home-page: https://github.com/OCA/web
License: LGPL-3
Author: ACSONE SA/NV,AdaptiveCity,Odoo Community Association (OCA)
Author-email: support@odoo-community.org
Classifier: Programming Language :: Python
Classifier: Framework :: Odoo
Classifier: Framework :: Odoo :: 18.0
Classifier: License :: OSI Approved :: GNU Lesser General Public License v3 (LGPLv3)
Classifier: Development Status :: 5 - Production/Stable
